{
  "project_info": {
    "project_number": "480114538491",
    "firebase_url": "https://react-danceblue.firebaseio.com",
    "project_id": "react-danceblue",
    "storage_bucket": "react-danceblue.appspot.com"
  },
  "client": [
    {
      "client_info": {
        "mobilesdk_app_id": "1:480114538491:android:bfc77ffa8149f8bfa2bd5e",
        "android_client_info": {
          "package_name": "com.danceblue.dancebluemarathon"
        }
      },
      "oauth_client": [
        {
          "client_id": "480114538491-r9an8egfet593cem0fl0p9q7aege6v7j.apps.googleusercontent.com",
          "client_type": 3
        }
      ],
      "api_key": [
        {
          "current_key": "AIzaSyBID3gdG8kaWFogC1txgiPQFf2-LCYlgjU"
        }
      ],
      "services": {
        "appinvite_service": {
          "other_platform_oauth_client": [
            {
              "client_id": "480114538491-r9an8egfet593cem0fl0p9q7aege6v7j.apps.googleusercontent.com",
              "client_type": 3
            }
          ]
        }
      }
    }
  ],
  "configuration_version": "1"
}